{
  "CH": "+8",
  "LATEST": "2017-01-23 10:00",
  "chartInfos": [
    {
      "RWName": "跌倒评估",
      "RWInfos": [
        {
          "ZXSJ": "2017-01-08 5:08",
          "VALUE": "19",
          "ZXHS": "韩越",
          "DInfo": "1\\3\\4\\5\\6\r\n 注：1使用床栏 2使用约束带 3警示标示 4安全教育 5起床时有人搀扶 6 穿防滑鞋",
          "DGLX":"双腔支气管导管",
          "YCMXInfors": [
            {
              "MXFS": 2
            },
            {
              "MXFS": 0
            },
            {
              "MXFS": 2
            },
            {
              "MXFS": 5
            },
            {
              "MXFS": 2
            },
            {
              "MXFS": 0
            },
            {
              "MXFS": 2
            },
            {
              "MXFS": 5
            },
            {
              "MXFS": 2
            },
            {
              "MXFS": 2
            }
          ]
        },
        {
          "ZXSJ": "2017-01-09 12:08",
          "VALUE": "34",
          "ZXHS": "韩越",
          "DInfo": "1\\3\\4\\5\\6\r\n 注：1使用床栏 2使用约束带 3警示标示 4安全教育 5起床时有人搀扶 6 穿防滑鞋",
          "DGLX":"双腔支气管导管",
          "YCMXInfors": [
            {
              "MXFS": 2
            },
            {
              "MXFS": 0
            },
            {
              "MXFS": 2
            },
            {
              "MXFS": 5
            },
            {
              "MXFS": 2
            },
            {
              "MXFS": 0
            },
            {
              "MXFS": 2
            },
            {
              "MXFS": 5
            },
            {
              "MXFS": 2
            },
            {
              "MXFS": 2
            }
          ]
        },
        {
          "ZXSJ": "2017-01-10 20:16",
          "VALUE": "40",
          "ZXHS": "陆燕蓉",
          "DInfo": "1\\3\\4\r\n 注：1使用床栏 2使用约束带 3警示标示 4安全教育 5起床时有人搀扶 6 穿防滑鞋",
          "DGLX":"可冲洗型气管导管",
          "YCMXInfors": [
            {
              "MXFS": 1
            },
            {
              "MXFS": 2
            },
            {
              "MXFS": 6
            },
            {
              "MXFS": 2
            },
            {
              "MXFS": 5
            },
            {
              "MXFS": 3
            },
            {
              "MXFS": 2
            },
            {
              "MXFS": 5
            },
            {
              "MXFS": 2
            },
            {
              "MXFS": 2
            }
          ]
        }
      ]
    }
  ]
}